nostage/__init__.py
nostage/cli.py
nostage/config.py
nostage/hook.py
nostage-0.1.2.dist-info/licenses/LICENSE
nostage-0.1.2.dist-info/METADATA
nostage-0.1.2.dist-info/WHEEL
nostage-0.1.2.dist-info/entry_points.txt
nostage-0.1.2.dist-info/top_level.txt
nostage-0.1.2.dist-info/RECORD
