Metadata-Version: 2.4
Name: nostage
Version: 0.1.2
Summary: 🛡️ Protect files from accidental Git commits
Author: Gururagavendra
License: MIT
Project-URL: Homepage, https://github.com/Gururagavendra/nostage
Project-URL: Repository, https://github.com/Gururagavendra/nostage
Project-URL: Bug Tracker, https://github.com/Gururagavendra/nostage/issues
Keywords: git,hooks,cli,developer-tools,version-control
Classifier: Development Status :: 4 - Beta
Classifier: Intended Audience :: Developers
Classifier: Topic :: Software Development :: Version Control :: Git
Classifier: License :: OSI Approved :: MIT License
Classifier: Programming Language :: Python :: 3
Classifier: Programming Language :: Python :: 3.7
Classifier: Programming Language :: Python :: 3.8
Classifier: Programming Language :: Python :: 3.9
Classifier: Programming Language :: Python :: 3.10
Classifier: Programming Language :: Python :: 3.11
Requires-Python: >=3.7
License-File: LICENSE
Requires-Dist: click>=8.0.0
Requires-Dist: colorama>=0.4.4
Dynamic: license-file
